README.md
setup.py
py2g_utils/__init__.py
py2g_utils/arguments.py
py2g_utils/mean.py
py2g_utils/parallel.py
py2g_utils/progress.py
py2g_utils/time.py
py2g_utils.egg-info/PKG-INFO
py2g_utils.egg-info/SOURCES.txt
py2g_utils.egg-info/dependency_links.txt
py2g_utils.egg-info/top_level.txt