Metadata-Version: 2.1
Name: py2g-utils
Version: 1.0.1
Summary: Some python utilities
Home-page: https://github.com/habecker/py2g-utils
Author: Yannick Habecker
Author-email: dev@y2g.de
License: UNKNOWN
Platform: UNKNOWN
